README.txt
setup.py
./repoze/__init__.py
./repoze/what/__init__.py
./repoze/what/plugins/__init__.py
./repoze/what/plugins/config.py
./tests/__init__.py
./tests/test_config.py
repoze/__init__.py
repoze.what.plugins.config.egg-info/PKG-INFO
repoze.what.plugins.config.egg-info/SOURCES.txt
repoze.what.plugins.config.egg-info/dependency_links.txt
repoze.what.plugins.config.egg-info/entry_points.txt
repoze.what.plugins.config.egg-info/namespace_packages.txt
repoze.what.plugins.config.egg-info/not-zip-safe
repoze.what.plugins.config.egg-info/requires.txt
repoze.what.plugins.config.egg-info/top_level.txt
repoze/what/__init__.py
repoze/what/plugins/__init__.py
repoze/what/plugins/config.py
tests/__init__.py
tests/test_config.py