Metadata-Version: 1.0
Name: repoze.what.plugins.config
Version: 0.2.1
Summary: pastedeploy help methods for repoze.what.
Home-page: http://github.com/jdinuncio/repoze.what.plugins.config/tree/master
Author: Jose Dinuncio
Author-email: jdinunci@uc.edu.ve
License: BSD-derived (see http://www.repoze.org/LICENSE.txt)
Keywords: wsgi repoze what paste paster pastedeploy
Platform: UNKNOWN
